[
  {
    "label": "Brand Colors",
    "name": "brand_colors",
    "type": "group",
    "children": [
      {
        "label": "Brand Green",
        "name": "brand_green",
        "type": "color",
        "default": {
          "color": "#2D5016"
        }
      },
      {
        "label": "Brand Lime",
        "name": "brand_lime",
        "type": "color",
        "default": {
          "color": "#A3D977"
        }
      },
      {
        "label": "Lime Vibrant",
        "name": "brand_lime_vibrant",
        "type": "color",
        "default": {
          "color": "#BEF264"
        }
      },
      {
        "label": "Brand Orange",
        "name": "brand_orange",
        "type": "color",
        "default": {
          "color": "#EC5B13"
        }
      },
      {
        "label": "Forest",
        "name": "forest",
        "type": "color",
        "default": {
          "color": "#2D5016"
        }
      },
      {
        "label": "Dark Slate (Text)",
        "name": "dark_slate",
        "type": "color",
        "default": {
          "color": "#0f172a"
        }
      }
    ]
  },
  {
    "label": "Backgrounds",
    "name": "backgrounds",
    "type": "group",
    "children": [
      {
        "label": "Light",
        "name": "light",
        "type": "group",
        "children": [
          {
            "label": "Background Light",
            "name": "background_light",
            "type": "color",
            "default": {
              "color": "#fdfefc"
            }
          },
          {
            "label": "Background Alt Light",
            "name": "background_alt_light",
            "type": "color",
            "default": {
              "color": "#f3f6f1"
            }
          }
        ]
      },
      {
        "label": "Dark",
        "name": "dark",
        "type": "group",
        "children": [
          {
            "label": "Background Dark",
            "name": "background_dark",
            "type": "color",
            "default": {
              "color": "#070a07"
            }
          },
          {
            "label": "Background Alt Dark",
            "name": "background_alt_dark",
            "type": "color",
            "default": {
              "color": "#0f170f"
            }
          },
          {
            "label": "Card Dark",
            "name": "card_dark",
            "type": "color",
            "default": {
              "color": "#162216"
            }
          }
        ]
      }
    ]
  },
  {
    "label": "Typography",
    "name": "typography",
    "type": "group",
    "children": [
      {
        "label": "Display (Headings)",
        "name": "display",
        "type": "font",
        "default": {
          "font": "Public Sans",
          "font_set": "GOOGLE",
          "fallback": "sans-serif"
        }
      },
      {
        "label": "Sans (Body)",
        "name": "sans",
        "type": "font",
        "default": {
          "font": "Public Sans",
          "font_set": "GOOGLE",
          "fallback": "sans-serif"
        }
      },
      {
        "label": "Mono (Code)",
        "name": "mono",
        "type": "font",
        "default": {
          "font": "Fira Code",
          "font_set": "GOOGLE",
          "fallback": "monospace"
        }
      }
    ]
  },

  {
    "label": "Spacing",
    "name": "spacing",
    "type": "group",
    "children": [
      {
        "label": "Vertical spacing",
        "name": "vertical_spacing",
        "type": "number",
        "display": "slider",
        "max": 500,
        "min": 0,
        "suffix": "px",
        "default": 80
      },
      {
        "label": "Maximum content width",
        "name": "maximum_content_width",
        "type": "number",
        "display": "slider",
        "max": 2500,
        "min": 900,
        "suffix": "px",
        "default": 1240
      }
    ]
  },
  {
    "label": "Text",
    "name": "text",
    "type": "group",
    "children": [
      {
        "label": "Heading one (H1)",
        "name": "h1",
        "type": "group",
        "children": [
          {
            "label": "Font",
            "name": "font",
            "type": "font",
            "inherited_value": {
              "property_value_paths": {
                "color": "theme.typography.display.color",
                "fallback": "theme.typography.display.fallback",
                "font": "theme.typography.display.font",
                "font_set": "theme.typography.display.font_set"
              }
            },
            "default": {
              "size": 50,
              "size_unit": "px",
              "styles": {
                "text-decoration": "none"
              },
              "variant": "700"
            }
          },
          {
            "label": "Transform",
            "name": "transform",
            "type": "choice",
            "choices": [
              ["none", "None"],
              ["capitalize", "Capitalize"],
              ["uppercase", "Uppercase"],
              ["lowercase", "Lowercase"]
            ],
            "display": "select",
            "default": "none"
          }
        ]
      },
      {
        "label": "Heading two (H2)",
        "name": "h2",
        "type": "group",
        "children": [
          {
            "label": "Font",
            "name": "font",
            "type": "font",
            "inherited_value": {
              "property_value_paths": {
                "color": "theme.typography.display.color",
                "fallback": "theme.typography.display.fallback",
                "font": "theme.typography.display.font",
                "font_set": "theme.typography.display.font_set"
              }
            },
            "default": {
              "size": 38,
              "size_unit": "px",
              "styles": {
                "text-decoration": "none"
              },
              "variant": "700"
            }
          },
          {
            "label": "Transform",
            "name": "transform",
            "type": "choice",
            "choices": [
              ["none", "None"],
              ["capitalize", "Capitalize"],
              ["uppercase", "Uppercase"],
              ["lowercase", "Lowercase"]
            ],
            "display": "select",
            "default": "none"
          }
        ]
      },
      {
        "label": "Heading three (H3)",
        "name": "h3",
        "type": "group",
        "children": [
          {
            "label": "Font",
            "name": "font",
            "type": "font",
            "inherited_value": {
              "property_value_paths": {
                "color": "theme.typography.display.color",
                "fallback": "theme.typography.display.fallback",
                "font": "theme.typography.display.font",
                "font_set": "theme.typography.display.font_set"
              }
            },
            "default": {
              "size": 30,
              "size_unit": "px",
              "styles": {
                "text-decoration": "none"
              },
              "variant": "700"
            }
          },
          {
            "label": "Transform",
            "name": "transform",
            "type": "choice",
            "choices": [
              ["none", "None"],
              ["capitalize", "Capitalize"],
              ["uppercase", "Uppercase"],
              ["lowercase", "Lowercase"]
            ],
            "display": "select",
            "default": "none"
          }
        ]
      },
      {
        "label": "Heading four (H4)",
        "name": "h4",
        "type": "group",
        "children": [
          {
            "label": "Font",
            "name": "font",
            "type": "font",
            "inherited_value": {
              "property_value_paths": {
                "color": "theme.typography.display.color",
                "fallback": "theme.typography.display.fallback",
                "font": "theme.typography.display.font",
                "font_set": "theme.typography.display.font_set"
              }
            },
            "default": {
              "size": 24,
              "size_unit": "px",
              "styles": {
                "text-decoration": "none"
              }
            }
          },
          {
            "label": "Transform",
            "name": "transform",
            "type": "choice",
            "choices": [
              ["none", "None"],
              ["capitalize", "Capitalize"],
              ["uppercase", "Uppercase"],
              ["lowercase", "Lowercase"]
            ],
            "display": "select",
            "default": "none"
          }
        ]
      },
      {
        "label": "Heading five (H5)",
        "name": "h5",
        "type": "group",
        "children": [
          {
            "label": "Font",
            "name": "font",
            "type": "font",
            "inherited_value": {
              "property_value_paths": {
                "color": "theme.typography.display.color",
                "fallback": "theme.typography.display.fallback",
                "font": "theme.typography.display.font",
                "font_set": "theme.typography.display.font_set"
              }
            },
            "default": {
              "color": "#000000",
              "size": 16,
              "size_unit": "px",
              "styles": {
                "text-decoration": "none"
              }
            }
          },
          {
            "label": "Transform",
            "name": "transform",
            "type": "choice",
            "choices": [
              ["none", "None"],
              ["capitalize", "Capitalize"],
              ["uppercase", "Uppercase"],
              ["lowercase", "Lowercase"]
            ],
            "display": "select",
            "default": "none"
          }
        ]
      },
      {
        "label": "Heading six (H6)",
        "name": "h6",
        "type": "group",
        "children": [
          {
            "label": "Font",
            "name": "font",
            "type": "font",
            "inherited_value": {
              "property_value_paths": {
                "color": "theme.typography.display.color",
                "fallback": "theme.typography.display.fallback",
                "font": "theme.typography.display.font",
                "font_set": "theme.typography.display.font_set"
              }
            },
            "default": {
              "size": 14,
              "size_unit": "px",
              "styles": {
                "text-decoration": "none"
              }
            }
          },
          {
            "label": "Transform",
            "name": "transform",
            "type": "choice",
            "choices": [
              ["none", "None"],
              ["capitalize", "Capitalize"],
              ["uppercase", "Uppercase"],
              ["lowercase", "Lowercase"]
            ],
            "display": "select",
            "default": "none"
          }
        ]
      },
      {
        "label": "Body",
        "name": "body_font",
        "type": "group",
        "children": [
          {
            "label": "Font",
            "name": "font",
            "type": "font",
            "visibility": {
              "hidden_subfields": {
                "styles": true
              }
            },
            "inherited_value": {
              "property_value_paths": {
                "color": "theme.typography.sans.color",
                "fallback": "theme.typography.sans.fallback",
                "font": "theme.typography.sans.font",
                "font_set": "theme.typography.sans.font_set"
              }
            },
            "default": {
              "size": 24,
              "size_unit": "px"
            }
          }
        ]
      },
      {
        "label": "Links",
        "name": "links",
        "type": "group",
        "children": [
          {
            "label": "Font",
            "name": "font",
            "type": "font",
            "visibility": {
              "hidden_subfields": {
                "size": true
              }
            },
            "inherited_value": {
              "property_value_paths": {
                "fallback": "theme.typography.sans.fallback",
                "font": "theme.typography.sans.font",
                "font_set": "theme.typography.sans.font_set"
              }
            },
            "default": {
              "color": "#0270E0",
              "styles": {
                "text-decoration": "underline"
              }
            }
          }
        ]
      }
    ]
  },
  {
    "label": "Buttons",
    "name": "buttons",
    "type": "group",
    "children": [
      {
        "label": "Text",
        "name": "text",
        "type": "group",
        "children": [
          {
            "label": "Font",
            "name": "font",
            "type": "font",
            "inherited_value": {
              "property_value_paths": {
                "fallback": "theme.typography.sans.fallback",
                "font": "theme.typography.sans.font",
                "font_set": "theme.typography.sans.font_set"
              }
            },
            "default": {
              "color": "#FFFFFF",
              "size": 22,
              "size_unit": "px"
            }
          },
          {
            "label": "Transform",
            "name": "transform",
            "type": "choice",
            "choices": [
              ["none", "None"],
              ["capitalize", "Capitalize"],
              ["uppercase", "Uppercase"],
              ["lowercase", "Lowercase"]
            ],
            "display": "select",
            "default": "none"
          }
        ]
      },
      {
        "label": "Background",
        "name": "background",
        "type": "group",
        "children": [
          {
            "label": "Color",
            "name": "color",
            "type": "color",
            "inherited_value": {
              "property_value_paths": {
                "color": "theme.brand_colors.brand_green.color"
              }
            },
            "default": {
              "opacity": 100
            }
          }
        ]
      },
      {
        "label": "Border",
        "name": "border",
        "type": "group",
        "children": [
          {
            "label": "Border",
            "name": "border",
            "type": "border",
            "inherited_value": {
              "property_value_paths": {
                "top.color": "theme.buttons.background.color.color",
                "right.color": "theme.buttons.background.color.color",
                "bottom.color": "theme.buttons.background.color.color",
                "left.color": "theme.buttons.background.color.color"
              }
            },
            "default": {
              "top": {
                "width": {
                  "value": 1,
                  "units": "px"
                },
                "opacity": 100,
                "style": "solid",
                "color": "#494A52"
              },
              "right": {
                "width": {
                  "value": 1,
                  "units": "px"
                },
                "opacity": 100,
                "style": "solid",
                "color": "#494A52"
              },
              "bottom": {
                "width": {
                  "value": 1,
                  "units": "px"
                },
                "opacity": 100,
                "style": "solid",
                "color": "#494A52"
              },
              "left": {
                "width": {
                  "value": 1,
                  "units": "px"
                },
                "opacity": 100,
                "style": "solid",
                "color": "#494A52"
              }
            }
          }
        ]
      },
      {
        "label": "Corner",
        "name": "corner",
        "type": "group",
        "children": [
          {
            "label": "Radius",
            "name": "radius",
            "type": "number",
            "display": "text",
            "max": 100,
            "step": 1,
            "suffix": "px",
            "default": 6
          }
        ]
      },
      {
        "label": "Spacing",
        "name": "spacing",
        "type": "group",
        "children": [
          {
            "label": "Spacing",
            "name": "spacing",
            "type": "spacing",
            "visibility": {
              "hidden_subfields": {
                "margin": true
              }
            },
            "default": {
              "padding": {
                "top": {
                  "value": 15,
                  "units": "px"
                },
                "right": {
                  "value": 53,
                  "units": "px"
                },
                "bottom": {
                  "value": 15,
                  "units": "px"
                },
                "left": {
                  "value": 53,
                  "units": "px"
                }
              }
            }
          }
        ]
      },
      {
        "label": "Hover",
        "name": "hover",
        "type": "group",
        "children": [
          {
            "label": "Text",
            "name": "text",
            "type": "group",
            "children": [
              {
                "label": "Color",
                "name": "color",
                "type": "color",
                "default": {
                  "color": "#ffffff",
                  "opacity": 100
                }
              }
            ]
          },
          {
            "label": "Background",
            "name": "background",
            "type": "group",
            "children": [
              {
                "label": "Color",
                "name": "color",
                "type": "color",
                "default": {
                  "opacity": 100,
                  "color": "#1a334e"
                }
              }
            ]
          },
          {
            "label": "Border",
            "name": "border",
            "type": "group",
            "children": [
              {
                "label": "Border",
                "name": "border",
                "type": "border",
                "default": {
                  "top": {
                    "width": {
                      "value": 1,
                      "units": "px"
                    },
                    "opacity": 100,
                    "style": "solid",
                    "color": "#1a334e"
                  },
                  "right": {
                    "width": {
                      "value": 1,
                      "units": "px"
                    },
                    "opacity": 100,
                    "style": "solid",
                    "color": "#1a334e"
                  },
                  "bottom": {
                    "width": {
                      "value": 1,
                      "units": "px"
                    },
                    "opacity": 100,
                    "style": "solid",
                    "color": "#1a334e"
                  },
                  "left": {
                    "width": {
                      "value": 1,
                      "units": "px"
                    },
                    "opacity": 100,
                    "style": "solid",
                    "color": "#1a334e"
                  }
                }
              }
            ]
          },
          {
            "label": "Corner",
            "name": "corner",
            "type": "group",
            "children": [
              {
                "label": "Radius",
                "name": "radius",
                "type": "number",
                "display": "text",
                "max": 100,
                "step": 1,
                "suffix": "px",
                "default": 6
              }
            ]
          }
        ]
      }
    ]
  },
  {
    "label": "Forms",
    "name": "forms",
    "type": "group",
    "children": [
      {
        "label": "Title",
        "name": "title",
        "type": "group",
        "children": [
          {
            "label": "Background",
            "name": "background",
            "type": "group",
            "children": [
              {
                "label": "Color",
                "name": "color",
                "type": "color",
                "inherited_value": {
                  "property_value_paths": {
                    "color": "theme.brand_colors.brand_lime.color"
                  }
                },
                "default": {
                  "opacity": 100
                }
              }
            ]
          },
          {
            "label": "Text",
            "name": "text",
            "type": "group",
            "children": [
              {
                "label": "Font",
                "name": "font",
                "type": "font",
                "inherited_value": {
                  "property_value_paths": {
                    "size": "theme.text.h3.font.size",
                    "font": "theme.typography.display.font",
                    "font_set": "theme.typography.display.font_set",
                    "color": "theme.typography.display.color",
                    "variant": "theme.text.h3.font.variant"
                  }
                },
                "load_external_fonts": true,
                "default": {
                  "size_unit": "px",
                  "styles": {}
                }
              }
            ]
          },
          {
            "label": "Border",
            "name": "border",
            "type": "group",
            "children": [
              {
                "label": "Border",
                "name": "border",
                "type": "border",
                "allow_custom_border_sides": true,
                "inherited_value": {
                  "property_value_paths": {
                    "top.color": "theme.forms.title.background.color.color",
                    "right.color": "theme.forms.title.background.color.color",
                    "bottom.color": "theme.forms.title.background.color.color",
                    "left.color": "theme.forms.title.background.color.color"
                  }
                },
                "default": {
                  "top": {
                    "width": {
                      "value": 1,
                      "units": "px"
                    },
                    "opacity": 100,
                    "style": "none",
                    "color": "#516747"
                  },
                  "right": {
                    "width": {
                      "value": 1,
                      "units": "px"
                    },
                    "opacity": 100,
                    "style": "none",
                    "color": "#516747"
                  },
                  "bottom": {
                    "width": {
                      "value": 1,
                      "units": "px"
                    },
                    "opacity": 100,
                    "style": "none",
                    "color": "#516747"
                  },
                  "left": {
                    "width": {
                      "value": 1,
                      "units": "px"
                    },
                    "opacity": 100,
                    "style": "none",
                    "color": "#516747"
                  }
                }
              }
            ]
          },
          {
            "label": "Spacing",
            "name": "spacing",
            "type": "group",
            "children": [
              {
                "label": "Spacing",
                "name": "spacing",
                "type": "spacing",
                "visibility": {
                  "hidden_subfields": {
                    "margin": true
                  }
                },
                "default": {
                  "padding": {
                    "top": {
                      "value": 0,
                      "units": "px"
                    },
                    "right": {
                      "value": 0,
                      "units": "px"
                    },
                    "bottom": {
                      "value": 30,
                      "units": "px"
                    },
                    "left": {
                      "value": 0,
                      "units": "px"
                    }
                  }
                }
              }
            ]
          },
          {
            "label": "Corner",
            "name": "corner",
            "type": "group",
            "children": [
              {
                "label": "Top Left Radius",
                "name": "top_left_radius",
                "type": "number",
                "display": "text",
                "max": 100,
                "step": 1,
                "suffix": "px",
                "default": 0
              },
              {
                "label": "Top Right Radius",
                "name": "top_right_radius",
                "type": "number",
                "display": "text",
                "max": 100,
                "step": 1,
                "suffix": "px",
                "default": 0
              },
              {
                "label": "Bottom Left Radius",
                "name": "bottom_left_radius",
                "type": "number",
                "display": "text",
                "max": 100,
                "step": 1,
                "suffix": "px",
                "default": 0
              },
              {
                "label": "Bottom Right Radius",
                "name": "bottom_right_radius",
                "type": "number",
                "display": "text",
                "max": 100,
                "step": 1,
                "suffix": "px",
                "default": 0
              }
            ]
          }
        ]
      },
      {
        "label": "Labels",
        "name": "labels",
        "type": "group",
        "children": [
          {
            "label": "Text",
            "name": "text",
            "type": "group",
            "children": [
              {
                "label": "Color",
                "name": "color",
                "type": "color",
                "visibility": {
                  "hidden_subfields": {
                    "opacity": true
                  }
                },
                "inherited_value": {
                  "property_value_paths": {
                    "color": "theme.typography.sans.color"
                  }
                }
              }
            ]
          }
        ]
      },
      {
        "label": "Help text",
        "name": "help_text",
        "type": "group",
        "children": [
          {
            "label": "Text",
            "name": "text",
            "type": "group",
            "children": [
              {
                "label": "Color",
                "name": "color",
                "type": "color",
                "visibility": {
                  "hidden_subfields": {
                    "opacity": true
                  }
                },
                "inherited_value": {
                  "property_value_paths": {
                    "color": "theme.typography.sans.color"
                  }
                }
              }
            ]
          }
        ]
      },
      {
        "label": "Fields",
        "name": "fields",
        "type": "group",
        "children": [
          {
            "label": "Placeholder",
            "name": "placeholder",
            "type": "group",
            "children": [
              {
                "label": "Color",
                "name": "color",
                "type": "color",
                "visibility": {
                  "hidden_subfields": {
                    "opacity": true
                  }
                },
                "inherited_value": {
                  "property_value_paths": {
                    "color": "theme.typography.sans.color"
                  }
                }
              }
            ]
          },
          {
            "label": "Text",
            "name": "text",
            "type": "group",
            "children": [
              {
                "label": "Color",
                "name": "color",
                "type": "color",
                "visibility": {
                  "hidden_subfields": {
                    "opacity": true
                  }
                },
                "inherited_value": {
                  "property_value_paths": {
                    "color": "theme.typography.sans.color"
                  }
                }
              }
            ]
          },
          {
            "label": "Background",
            "name": "background",
            "type": "group",
            "children": [
              {
                "label": "Color",
                "name": "color",
                "type": "color",
                "default": {
                  "color": "#FFFFFF",
                  "opacity": 100
                }
              }
            ]
          },
          {
            "label": "Border",
            "name": "border",
            "type": "group",
            "children": [
              {
                "label": "Border",
                "name": "border",
                "type": "border",
                "default": {
                  "top": {
                    "width": {
                      "value": 2,
                      "units": "px"
                    },
                    "opacity": 100,
                    "style": "solid",
                    "color": "#D1D6DC"
                  },
                  "right": {
                    "width": {
                      "value": 2,
                      "units": "px"
                    },
                    "opacity": 100,
                    "style": "solid",
                    "color": "#D1D6DC"
                  },
                  "bottom": {
                    "width": {
                      "value": 2,
                      "units": "px"
                    },
                    "opacity": 100,
                    "style": "solid",
                    "color": "#D1D6DC"
                  },
                  "left": {
                    "width": {
                      "value": 2,
                      "units": "px"
                    },
                    "opacity": 100,
                    "style": "solid",
                    "color": "#D1D6DC"
                  }
                }
              }
            ]
          },
          {
            "label": "Corner",
            "name": "corner",
            "type": "group",
            "children": [
              {
                "label": "Radius",
                "name": "radius",
                "type": "number",
                "display": "text",
                "max": 100,
                "step": 1,
                "suffix": "px",
                "default": 3
              }
            ]
          }
        ]
      },
      {
        "label": "Button",
        "name": "button",
        "type": "group",
        "children": [
          {
            "label": "Text",
            "name": "text",
            "type": "group",
            "children": [
              {
                "label": "Font",
                "name": "font",
                "type": "font",
                "inherited_value": {
                  "property_value_paths": {
                    "fallback": "theme.typography.sans.fallback",
                    "font": "theme.typography.sans.font",
                    "font_set": "theme.typography.sans.font_set"
                  }
                },
                "placeholder": "",
                "validation_regex": "",
                "default": {
                  "color": "#FFFFFF",
                  "size": 22,
                  "size_unit": "px"
                }
              }
            ]
          },
          {
            "label": "Border",
            "name": "border",
            "type": "group",
            "children": [
              {
                "label": "Border",
                "name": "border",
                "type": "border",
                "allow_custom_border_sides": false,
                "inherited_value": {
                  "property_value_paths": {
                    "top.color": "theme.brand_colors.brand_green.color",
                    "left.color": "theme.brand_colors.brand_green.color",
                    "right.color": "theme.brand_colors.brand_green.color",
                    "bottom.color": "theme.brand_colors.brand_green.color"
                  }
                },
                "default": {
                  "top": {
                    "width": {
                      "value": 1,
                      "units": "px"
                    },
                    "opacity": 100,
                    "style": "none"
                  },
                  "right": {
                    "width": {
                      "value": 1,
                      "units": "px"
                    },
                    "opacity": 100,
                    "style": "none"
                  },
                  "bottom": {
                    "width": {
                      "value": 1,
                      "units": "px"
                    },
                    "opacity": 100,
                    "style": "none"
                  },
                  "left": {
                    "width": {
                      "value": 1,
                      "units": "px"
                    },
                    "opacity": 100,
                    "style": "none"
                  }
                }
              }
            ]
          },
          {
            "label": "Background",
            "name": "background",
            "type": "group",
            "children": [
              {
                "label": "Color",
                "name": "color",
                "type": "color",
                "inherited_value": {
                  "property_value_paths": {
                    "color": "theme.brand_colors.brand_green.color"
                  }
                },
                "default": {
                  "opacity": 100
                }
              }
            ]
          },
          {
            "label": "Spacing",
            "name": "spacing",
            "type": "group",
            "children": [
              {
                "label": "Spacing",
                "name": "spacing",
                "type": "spacing",
                "visibility": {
                  "hidden_subfields": {
                    "margin": true
                  }
                },
                "inherited_value": {
                  "property_value_paths": {
                    "padding": "theme.buttons.spacing.spacing.padding"
                  }
                },
                "default": {
                  "padding": {
                    "top": {
                      "value": 0,
                      "units": "px"
                    },
                    "right": {
                      "value": 0,
                      "units": "px"
                    },
                    "bottom": {
                      "value": 0,
                      "units": "px"
                    },
                    "left": {
                      "value": 0,
                      "units": "px"
                    }
                  }
                }
              }
            ]
          },
          {
            "label": "Hover",
            "name": "hover",
            "type": "group",
            "children": [
              {
                "label": "Background",
                "name": "background",
                "type": "group",
                "children": [
                  {
                    "label": "Color",
                    "name": "color",
                    "type": "color",
                    "default": {
                      "opacity": 100,
                      "color": "#1a334e"
                    }
                  }
                ]
              },
              {
                "label": "Border",
                "name": "border",
                "type": "group",
                "children": [
                  {
                    "label": "Border",
                    "name": "border",
                    "type": "border",
                    "allow_custom_border_sides": false,
                    "default": {
                      "top": {
                        "width": {
                          "value": 1,
                          "units": "px"
                        },
                        "color": "#1a334e",
                        "opacity": 100,
                        "style": "none"
                      },
                      "right": {
                        "width": {
                          "value": 1,
                          "units": "px"
                        },
                        "color": "#1a334e",
                        "opacity": 100,
                        "style": "none"
                      },
                      "bottom": {
                        "width": {
                          "value": 1,
                          "units": "px"
                        },
                        "color": "#1a334e",
                        "opacity": 100,
                        "style": "none"
                      },
                      "left": {
                        "width": {
                          "value": 1,
                          "units": "px"
                        },
                        "color": "#1a334e",
                        "opacity": 100,
                        "style": "none"
                      }
                    }
                  }
                ]
              },
              {
                "label": "Text",
                "name": "text",
                "type": "group",
                "children": [
                  {
                    "label": "Color",
                    "name": "color",
                    "type": "color",
                    "visibility": {
                      "hidden_subfields": {
                        "opacity": true
                      }
                    },
                    "default": {
                      "color": "#ffffff"
                    }
                  }
                ]
              }
            ]
          }
        ]
      },
      {
        "label": "Form",
        "name": "form",
        "type": "group",
        "children": [
          {
            "label": "Background",
            "name": "background",
            "type": "group",
            "children": [
              {
                "label": "Color",
                "name": "color",
                "type": "color",
                "inherited_value": {
                  "property_value_paths": {
                    "color": "theme.brand_colors.brand_lime.color"
                  }
                },
                "default": {
                  "opacity": 100
                }
              }
            ]
          },
          {
            "label": "Spacing",
            "name": "spacing",
            "type": "group",
            "children": [
              {
                "label": "Spacing",
                "name": "spacing",
                "type": "spacing",
                "visibility": {
                  "hidden_subfields": {
                    "margin": true
                  }
                },
                "default": {
                  "padding": {
                    "top": {
                      "value": 0,
                      "units": "px"
                    },
                    "right": {
                      "value": 0,
                      "units": "px"
                    },
                    "bottom": {
                      "value": 0,
                      "units": "px"
                    },
                    "left": {
                      "value": 0,
                      "units": "px"
                    }
                  }
                }
              }
            ]
          },
          {
            "label": "Border",
            "name": "border",
            "type": "group",
            "children": [
              {
                "label": "Border",
                "name": "border",
                "type": "border",
                "allow_custom_border_sides": true,
                "inherited_value": {
                  "property_value_paths": {
                    "top.color": "theme.forms.form.background.color.color",
                    "right.color": "theme.forms.form.background.color.color",
                    "bottom.color": "theme.forms.form.background.color.color",
                    "left.color": "theme.forms.form.background.color.color"
                  }
                },
                "default": {
                  "top": {
                    "width": {
                      "value": 1,
                      "units": "px"
                    },
                    "opacity": 100,
                    "style": "none",
                    "color": "#f4f0ec"
                  },
                  "right": {
                    "width": {
                      "value": 1,
                      "units": "px"
                    },
                    "opacity": 100,
                    "style": "none",
                    "color": "#f4f0ec"
                  },
                  "bottom": {
                    "width": {
                      "value": 1,
                      "units": "px"
                    },
                    "opacity": 100,
                    "style": "none",
                    "color": "#f4f0ec"
                  },
                  "left": {
                    "width": {
                      "value": 1,
                      "units": "px"
                    },
                    "opacity": 100,
                    "style": "none",
                    "color": "#f4f0ec"
                  }
                }
              }
            ]
          },
          {
            "label": "Corner",
            "name": "corner",
            "type": "group",
            "children": [
              {
                "label": "Top Left Radius",
                "name": "top_left_radius",
                "type": "number",
                "display": "text",
                "max": 100,
                "step": 1,
                "suffix": "px",
                "default": 0
              },
              {
                "label": "Top Right Radius",
                "name": "top_right_radius",
                "type": "number",
                "display": "text",
                "max": 100,
                "step": 1,
                "suffix": "px",
                "default": 0
              },
              {
                "label": "Bottom Left Radius",
                "name": "bottom_left_radius",
                "type": "number",
                "display": "text",
                "max": 100,
                "step": 1,
                "suffix": "px",
                "default": 0
              },
              {
                "label": "Bottom Right Radius",
                "name": "bottom_right_radius",
                "type": "number",
                "display": "text",
                "max": 100,
                "step": 1,
                "suffix": "px",
                "default": 0
              }
            ]
          }
        ]
      }
    ]
  },
  {
    "label": "Tables",
    "name": "tables",
    "type": "group",
    "children": [
      {
        "label": "Header",
        "name": "header",
        "type": "group",
        "children": [
          {
            "label": "Text",
            "name": "text",
            "type": "group",
            "children": [
              {
                "label": "Color",
                "name": "color",
                "type": "color",
                "visibility": {
                  "hidden_subfields": {
                    "opacity": true
                  }
                },
                "default": {
                  "color": "#FFFFFF"
                }
              }
            ]
          },
          {
            "label": "Background",
            "name": "background",
            "type": "group",
            "children": [
              {
                "label": "Color",
                "name": "color",
                "type": "color",
                "inherited_value": {
                  "property_value_paths": {
                    "color": "theme.brand_colors.brand_green.color"
                  }
                },
                "default": {
                  "opacity": 100
                }
              }
            ]
          }
        ]
      },
      {
        "label": "Body",
        "name": "table_body",
        "type": "group",
        "children": [
          {
            "label": "Text",
            "name": "text",
            "type": "group",
            "children": [
              {
                "label": "Color",
                "name": "color",
                "type": "color",
                "visibility": {
                  "hidden_subfields": {
                    "opacity": true
                  }
                },
                "inherited_value": {
                  "property_value_paths": {
                    "color": "theme.typography.sans.color"
                  }
                }
              }
            ]
          },
          {
            "label": "Background",
            "name": "background",
            "type": "group",
            "children": [
              {
                "label": "Color",
                "name": "color",
                "type": "color",
                "default": {
                  "color": "#FFFFFF",
                  "opacity": 100
                }
              }
            ]
          }
        ]
      },
      {
        "label": "Footer",
        "name": "footer",
        "type": "group",
        "children": [
          {
            "label": "Text",
            "name": "text",
            "type": "group",
            "children": [
              {
                "label": "Color",
                "name": "color",
                "type": "color",
                "visibility": {
                  "hidden_subfields": {
                    "opacity": true
                  }
                },
                "inherited_value": {
                  "property_value_paths": {
                    "color": "theme.typography.sans.color"
                  }
                }
              }
            ]
          },
          {
            "label": "Background",
            "name": "background",
            "type": "group",
            "children": [
              {
                "label": "Color",
                "name": "color",
                "type": "color",
                "default": {
                  "color": "#FFFFFF",
                  "opacity": 100
                }
              }
            ]
          }
        ]
      },
      {
        "label": "Cells",
        "name": "cells",
        "type": "group",
        "children": [
          {
            "label": "Spacing",
            "name": "spacing",
            "type": "group",
            "children": [
              {
                "label": "Spacing",
                "name": "spacing",
                "type": "spacing",
                "visibility": {
                  "hidden_subfields": {
                    "margin": true
                  }
                },
                "default": {
                  "padding": {
                    "top": {
                      "value": 18,
                      "units": "px"
                    },
                    "right": {
                      "value": 18,
                      "units": "px"
                    },
                    "bottom": {
                      "value": 18,
                      "units": "px"
                    },
                    "left": {
                      "value": 18,
                      "units": "px"
                    }
                  }
                }
              }
            ]
          },
          {
            "label": "Border",
            "name": "border",
            "type": "group",
            "children": [
              {
                "label": "Border",
                "name": "border",
                "type": "border",
                "inherited_value": {
                  "property_value_paths": {
                    "top.color": "theme.typography.sans.color",
                    "right.color": "theme.typography.sans.color",
                    "bottom.color": "theme.typography.sans.color",
                    "left.color": "theme.typography.sans.color"
                  }
                },
                "default": {
                  "top": {
                    "width": {
                      "value": 1,
                      "units": "px"
                    },
                    "opacity": 100,
                    "style": "solid",
                    "color": "#494A52"
                  },
                  "right": {
                    "width": {
                      "value": 1,
                      "units": "px"
                    },
                    "opacity": 100,
                    "style": "solid",
                    "color": "#494A52"
                  },
                  "bottom": {
                    "width": {
                      "value": 1,
                      "units": "px"
                    },
                    "opacity": 100,
                    "style": "solid",
                    "color": "#494A52"
                  },
                  "left": {
                    "width": {
                      "value": 1,
                      "units": "px"
                    },
                    "opacity": 100,
                    "style": "solid",
                    "color": "#494A52"
                  }
                }
              }
            ]
          }
        ]
      }
    ]
  },
  {
    "label": "Website header",
    "name": "header",
    "type": "group",
    "children": [
      {
        "label": "Menu",
        "name": "menu",
        "type": "group",
        "children": [
          {
            "label": "Text",
            "name": "text",
            "type": "group",
            "children": [
              {
                "label": "Color",
                "name": "color",
                "type": "color",
                "visibility": {
                  "hidden_subfields": {
                    "opacity": true
                  }
                },
                "inherited_value": {
                  "property_value_paths": {
                    "color": "theme.typography.sans.color"
                  }
                }
              }
            ]
          },
          {
            "label": "Drop downs",
            "name": "drop_downs",
            "type": "group",
            "children": [
              {
                "label": "Text",
                "name": "text",
                "type": "group",
                "children": [
                  {
                    "label": "Color",
                    "name": "color",
                    "type": "color",
                    "visibility": {
                      "hidden_subfields": {
                        "opacity": true
                      }
                    },
                    "inherited_value": {
                      "property_value_paths": {
                        "color": "theme.typography.sans.color"
                      }
                    }
                  }
                ]
              },
              {
                "label": "Background",
                "name": "background",
                "type": "group",
                "children": [
                  {
                    "label": "Color",
                    "name": "color",
                    "type": "color",
                    "default": {
                      "color": "#FFFFFF",
                      "opacity": 100
                    }
                  }
                ]
              },
              {
                "label": "Border",
                "name": "border",
                "type": "group",
                "children": [
                  {
                    "label": "Border",
                    "name": "border",
                    "type": "border",
                    "inherited_value": {
                      "property_value_paths": {
                        "top.color": "theme.brand_colors.brand_green.color",
                        "right.color": "theme.brand_colors.brand_green.color",
                        "bottom.color": "theme.brand_colors.brand_green.color",
                        "left.color": "theme.brand_colors.brand_green.color"
                      }
                    },
                    "default": {
                      "top": {
                        "width": {
                          "value": 2,
                          "units": "px"
                        },
                        "opacity": 100,
                        "style": "solid",
                        "color": "#494A52"
                      },
                      "right": {
                        "width": {
                          "value": 2,
                          "units": "px"
                        },
                        "opacity": 100,
                        "style": "solid",
                        "color": "#494A52"
                      },
                      "bottom": {
                        "width": {
                          "value": 2,
                          "units": "px"
                        },
                        "opacity": 100,
                        "style": "solid",
                        "color": "#494A52"
                      },
                      "left": {
                        "width": {
                          "value": 2,
                          "units": "px"
                        },
                        "opacity": 100,
                        "style": "solid",
                        "color": "#494A52"
                      }
                    }
                  }
                ]
              }
            ]
          }
        ]
      },
      {
        "label": "Background",
        "name": "background",
        "type": "group",
        "children": [
          {
            "label": "Color",
            "name": "color",
            "type": "color",
            "inherited_value": {
              "property_value_paths": {
                "color": "theme.brand_colors.brand_lime.color"
              }
            },
            "default": {
              "opacity": 100
            }
          }
        ]
      }
    ]
  },
  {
    "label": "Website footer",
    "name": "footer",
    "type": "group",
    "children": [
      {
        "label": "Text",
        "name": "text",
        "type": "group",
        "children": [
          {
            "label": "Color",
            "name": "color",
            "type": "color",
            "visibility": {
              "hidden_subfields": {
                "opacity": true
              }
            },
            "inherited_value": {
              "property_value_paths": {
                "color": "theme.typography.sans.color"
              }
            }
          }
        ]
      },
      {
        "label": "Background",
        "name": "background",
        "type": "group",
        "children": [
          {
            "label": "Color",
            "name": "color",
            "type": "color",
            "inherited_value": {
              "property_value_paths": {
                "color": "theme.brand_colors.brand_lime.color"
              }
            },
            "default": {
              "opacity": 100
            }
          }
        ]
      }
    ]
  }
]
