[ {
  "id" : "cards",
  "name" : "cards",
  "label" : "Cards",
  "required" : false,
  "locked" : false,
  "occurrence" : {
    "min" : 1,
    "max" : 12,
    "sorting_label_field" : null,
    "default" : 3
  },
  "children" : [ {
    "id" : "cards.image",
    "name" : "image",
    "label" : "Image",
    "required" : false,
    "locked" : false,
    "responsive" : false,
    "resizable" : true,
    "show_loading" : false,
    "display_width" : null,
    "type" : "image",
    "default" : {
      "src" : "",
      "alt" : "Project image"
    }
  }, {
    "id" : "cards.tags",
    "name" : "tags",
    "label" : "Tags",
    "required" : false,
    "locked" : false,
    "occurrence" : {
      "min" : 0,
      "max" : 5,
      "sorting_label_field" : null,
      "default" : 2
    },
    "allow_new_line" : false,
    "display_width" : null,
    "type" : "text",
    "default" : [ "Custom Objects", "HubDB" ]
  }, {
    "id" : "cards.title",
    "name" : "title",
    "label" : "Title",
    "required" : false,
    "locked" : false,
    "allow_new_line" : false,
    "display_width" : null,
    "type" : "text",
    "default" : "Arquitectura CRM para Real Estate Global"
  }, {
    "id" : "cards.challenge",
    "name" : "challenge",
    "label" : "Challenge",
    "required" : false,
    "locked" : false,
    "children" : [ {
      "id" : "cards.challenge.heading",
      "name" : "heading",
      "label" : "Heading",
      "required" : false,
      "locked" : false,
      "allow_new_line" : false,
      "display_width" : null,
      "type" : "text",
      "default" : "El Reto (Arquitectura)"
    }, {
      "id" : "cards.challenge.description",
      "name" : "description",
      "label" : "Description",
      "required" : false,
      "locked" : false,
      "allow_new_line" : false,
      "display_width" : null,
      "type" : "text",
      "default" : "Centralizar un inventario de +5,000 propiedades dinámicas en 12 países, garantizando integridad de datos y filtrado en tiempo real sin latencia."
    } ],
    "tab" : "CONTENT",
    "expanded" : false,
    "group_occurrence_meta" : null,
    "display_width" : null,
    "type" : "group"
  }, {
    "id" : "cards.solution",
    "name" : "solution",
    "label" : "Solution",
    "required" : false,
    "locked" : false,
    "children" : [ {
      "id" : "cards.solution.heading",
      "name" : "heading",
      "label" : "Heading",
      "required" : false,
      "locked" : false,
      "allow_new_line" : false,
      "display_width" : null,
      "type" : "text",
      "default" : "La Solución (Desarrollo)"
    }, {
      "id" : "cards.solution.description",
      "name" : "description",
      "label" : "Description",
      "required" : false,
      "locked" : false,
      "allow_new_line" : false,
      "display_width" : null,
      "type" : "text",
      "default" : "Modelado de Objetos Personalizados vinculados a HubDB para visualización dinámica."
    } ],
    "tab" : "CONTENT",
    "expanded" : false,
    "group_occurrence_meta" : null,
    "display_width" : null,
    "type" : "group"
  }, {
    "id" : "cards.link",
    "name" : "link",
    "label" : "Link",
    "required" : false,
    "locked" : false,
    "supported_types" : [ "EXTERNAL", "CONTENT", "FILE", "EMAIL_ADDRESS", "BLOG" ],
    "show_advanced_rel_options" : false,
    "display_width" : null,
    "type" : "link",
    "default" : {
      "url" : {
        "href" : "#"
      }
    }
  }, {
    "id" : "cards.link_text",
    "name" : "link_text",
    "label" : "Link Text",
    "required" : false,
    "locked" : false,
    "allow_new_line" : false,
    "display_width" : null,
    "type" : "text",
    "default" : "Leer caso completo"
  }, {
    "id" : "cards.is_coming_soon",
    "name" : "is_coming_soon",
    "label" : "Coming Soon",
    "required" : false,
    "locked" : false,
    "display" : "checkbox",
    "display_width" : null,
    "type" : "boolean",
    "default" : false
  }, {
    "id" : "cards.coming_soon_label",
    "name" : "coming_soon_label",
    "label" : "Coming Soon Label",
    "required" : false,
    "locked" : false,
    "allow_new_line" : false,
    "display_width" : null,
    "type" : "text",
    "default" : "[ EN DESARROLLO ]"
  }, {
    "id" : "cards.coming_soon_description",
    "name" : "coming_soon_description",
    "label" : "Coming Soon Description",
    "required" : false,
    "locked" : false,
    "allow_new_line" : false,
    "display_width" : null,
    "type" : "text",
    "default" : ""
  }, {
    "id" : "cards.coming_soon_tech_stack",
    "name" : "coming_soon_tech_stack",
    "label" : "Coming Soon Tech Stack",
    "required" : false,
    "locked" : false,
    "allow_new_line" : false,
    "display_width" : null,
    "type" : "text",
    "default" : ""
  } ],
  "tab" : "CONTENT",
  "expanded" : false,
  "group_occurrence_meta" : null,
  "display_width" : null,
  "type" : "group",
  "default" : [ {
    "image" : {
      "src" : "",
      "alt" : "Project 1"
    },
    "tags" : [ "Custom Objects", "HubDB" ],
    "title" : "Arquitectura CRM para Real Estate Global",
    "challenge" : {
      "heading" : "El Reto (Arquitectura)",
      "description" : "Centralizar un inventario de +5,000 propiedades dinámicas en 12 países."
    },
    "solution" : {
      "heading" : "La Solución (Desarrollo)",
      "description" : "Modelado de Objetos Personalizados vinculados a HubDB para visualización dinámica."
    },
    "link" : {
      "url" : {
        "href" : "#"
      }
    },
    "link_text" : "Leer caso completo",
    "is_coming_soon" : false,
    "coming_soon_label" : "",
    "coming_soon_description" : "",
    "coming_soon_tech_stack" : ""
  }, {
    "image" : {
      "src" : "",
      "alt" : "Project 2"
    },
    "tags" : [ "HubSpot CMS", "API Integration" ],
    "title" : "Portal de Membresías con HubDB",
    "challenge" : {
      "heading" : "El Reto (Arquitectura)",
      "description" : "Creación de un área privada para 10,000 usuarios con contenido restringido."
    },
    "solution" : {
      "heading" : "La Solución (Desarrollo)",
      "description" : "Implementación de Webhooks y Serverless Functions para sincronizar estados de membresía."
    },
    "link" : {
      "url" : {
        "href" : "#"
      }
    },
    "link_text" : "Leer caso completo",
    "is_coming_soon" : false,
    "coming_soon_label" : "",
    "coming_soon_description" : "",
    "coming_soon_tech_stack" : ""
  }, {
    "image" : {
      "src" : "",
      "alt" : ""
    },
    "tags" : [ ],
    "title" : "Integración Enterprise ERP–HubSpot",
    "challenge" : {
      "heading" : "",
      "description" : ""
    },
    "solution" : {
      "heading" : "",
      "description" : ""
    },
    "link" : {
      "url" : {
        "href" : "#"
      }
    },
    "link_text" : "",
    "is_coming_soon" : true,
    "coming_soon_label" : "[ EN DESARROLLO ]",
    "coming_soon_description" : "Sincronización bidireccional compleja de inventarios y pedidos entre SAP y HubSpot utilizando middleware customizado sobre AWS Lambda.",
    "coming_soon_tech_stack" : "Tech Stack: AWS, Node.js, GraphQL"
  } ]
}, {
  "id" : "styles",
  "name" : "styles",
  "label" : "Styles",
  "required" : false,
  "locked" : false,
  "children" : [ {
    "id" : "styles.dark_mode_style",
    "name" : "dark_mode_style",
    "label" : "Dark Mode Style",
    "required" : false,
    "locked" : false,
    "display" : "radio",
    "choices" : [ [ "deep", "Deep Dark" ], [ "alt", "Alt Dark" ] ],
    "multiple" : false,
    "reordering_enabled" : true,
    "preset" : null,
    "display_width" : null,
    "type" : "choice",
    "default" : "alt"
  } ],
  "tab" : "STYLE",
  "expanded" : false,
  "group_occurrence_meta" : null,
  "display_width" : null,
  "type" : "group"
} ]